telicent_validation_tool/__init__.py
telicent_validation_tool/validators.py
telicent_validation_tool-0.2.1.dist-info/LICENSE
telicent_validation_tool-0.2.1.dist-info/METADATA
telicent_validation_tool-0.2.1.dist-info/NOTICE
telicent_validation_tool-0.2.1.dist-info/WHEEL
telicent_validation_tool-0.2.1.dist-info/top_level.txt
telicent_validation_tool-0.2.1.dist-info/RECORD
