Metadata-Version: 2.1
Name: telicent-validation-tool
Version: 0.2.1
Summary: A library for validating data before it is brought in to Telicnt CORE.
Author-email: Telicent Ltd <opensource@telicent.io>
License: Apache License
Project-URL: Repository, https://github.com/telicent-oss/validation-tool
Classifier: Programming Language :: Python :: 3.10
Classifier: Programming Language :: Python :: 3.11
Classifier: Programming Language :: Python :: 3.12
Classifier: Programming Language :: Python :: 3 :: Only
Classifier: Topic :: Software Development
Classifier: Typing :: Typed
Classifier: Operating System :: Microsoft :: Windows
Classifier: Operating System :: POSIX
Classifier: Operating System :: Unix
Classifier: Operating System :: MacOS
Requires-Python: >=3.11
License-File: LICENSE
License-File: NOTICE
Requires-Dist: jsonschema ==4.22.0
Requires-Dist: rdflib ==6.3.2
Requires-Dist: telicent-owl2shacl ==0.2.4
Provides-Extra: dev
Requires-Dist: pre-commit ==3.5.0 ; extra == 'dev'
Requires-Dist: ruff ==0.1.5 ; extra == 'dev'
Requires-Dist: mypy ==1.7.0 ; extra == 'dev'
Requires-Dist: coverage ==7.5.3 ; extra == 'dev'
